{
"type": "FeatureCollection",
"crs": { "type": "name", "properties": { "name": "urn:ogc:def:crs:OGC:1.3:CRS84" } },
"features": [
{ "type": "Feature", "properties": { "NAME": null, "NAME_EN": null, "RAILWAY": null, "HIGHWAY": "bus_stop", "REF": null, "NETWORK": null, "PUBLIC_TRA": null, "OSM_TYPE": "node", "OSM_ID": 278326528 }, "geometry": { "type": "Point", "coordinates": [ -68.32949330000001, 12.2387699 ] } },
{ "type": "Feature", "properties": { "NAME": null, "NAME_EN": null, "RAILWAY": null, "HIGHWAY": "bus_stop", "REF": null, "NETWORK": null, "PUBLIC_TRA": "platform", "OSM_TYPE": "node", "OSM_ID": 3746542413 }, "geometry": { "type": "Point", "coordinates": [ -68.262082400000011, 12.1418734 ] } },
{ "type": "Feature", "properties": { "NAME": null, "NAME_EN": null, "RAILWAY": null, "HIGHWAY": "bus_stop", "REF": null, "NETWORK": null, "PUBLIC_TRA": "platform", "OSM_TYPE": "node", "OSM_ID": 3746542414 }, "geometry": { "type": "Point", "coordinates": [ -68.266372600000011, 12.145078 ] } },
{ "type": "Feature", "properties": { "NAME": null, "NAME_EN": null, "RAILWAY": null, "HIGHWAY": "bus_stop", "REF": null, "NETWORK": null, "PUBLIC_TRA": "platform", "OSM_TYPE": "node", "OSM_ID": 3748219784 }, "geometry": { "type": "Point", "coordinates": [ -68.2613453, 12.1358674 ] } },
{ "type": "Feature", "properties": { "NAME": "Bushaite", "NAME_EN": null, "RAILWAY": null, "HIGHWAY": "bus_stop", "REF": null, "NETWORK": null, "PUBLIC_TRA": null, "OSM_TYPE": "node", "OSM_ID": 3752220370 }, "geometry": { "type": "Point", "coordinates": [ -68.3314715, 12.2330396 ] } },
{ "type": "Feature", "properties": { "NAME": null, "NAME_EN": null, "RAILWAY": null, "HIGHWAY": "bus_stop", "REF": null, "NETWORK": null, "PUBLIC_TRA": "platform", "OSM_TYPE": "node", "OSM_ID": 3753028110 }, "geometry": { "type": "Point", "coordinates": [ -68.264344200000011, 12.1625441 ] } },
{ "type": "Feature", "properties": { "NAME": null, "NAME_EN": null, "RAILWAY": null, "HIGHWAY": "bus_stop", "REF": null, "NETWORK": null, "PUBLIC_TRA": "platform", "OSM_TYPE": "node", "OSM_ID": 3754667590 }, "geometry": { "type": "Point", "coordinates": [ -68.2710102, 12.1633904 ] } },
{ "type": "Feature", "properties": { "NAME": null, "NAME_EN": null, "RAILWAY": null, "HIGHWAY": "bus_stop", "REF": null, "NETWORK": null, "PUBLIC_TRA": "platform", "OSM_TYPE": "node", "OSM_ID": 3754816494 }, "geometry": { "type": "Point", "coordinates": [ -68.2597712, 12.152371 ] } },
{ "type": "Feature", "properties": { "NAME": null, "NAME_EN": null, "RAILWAY": null, "HIGHWAY": "bus_stop", "REF": null, "NETWORK": null, "PUBLIC_TRA": "platform", "OSM_TYPE": "node", "OSM_ID": 3755122897 }, "geometry": { "type": "Point", "coordinates": [ -68.2716257, 12.1597737 ] } },
{ "type": "Feature", "properties": { "NAME": null, "NAME_EN": null, "RAILWAY": null, "HIGHWAY": "bus_stop", "REF": null, "NETWORK": null, "PUBLIC_TRA": null, "OSM_TYPE": "node", "OSM_ID": 3756373302 }, "geometry": { "type": "Point", "coordinates": [ -68.3330495, 12.2398182 ] } },
{ "type": "Feature", "properties": { "NAME": null, "NAME_EN": null, "RAILWAY": null, "HIGHWAY": "bus_stop", "REF": null, "NETWORK": null, "PUBLIC_TRA": "platform", "OSM_TYPE": "node", "OSM_ID": 3766625930 }, "geometry": { "type": "Point", "coordinates": [ -68.2746295, 12.1788216 ] } },
{ "type": "Feature", "properties": { "NAME": null, "NAME_EN": null, "RAILWAY": null, "HIGHWAY": "bus_stop", "REF": null, "NETWORK": null, "PUBLIC_TRA": "platform", "OSM_TYPE": "node", "OSM_ID": 3766625931 }, "geometry": { "type": "Point", "coordinates": [ -68.2753577, 12.1761853 ] } },
{ "type": "Feature", "properties": { "NAME": null, "NAME_EN": null, "RAILWAY": null, "HIGHWAY": "bus_stop", "REF": null, "NETWORK": null, "PUBLIC_TRA": "platform", "OSM_TYPE": "node", "OSM_ID": 3766625932 }, "geometry": { "type": "Point", "coordinates": [ -68.2726694, 12.1736408 ] } },
{ "type": "Feature", "properties": { "NAME": null, "NAME_EN": null, "RAILWAY": null, "HIGHWAY": "bus_stop", "REF": null, "NETWORK": null, "PUBLIC_TRA": "platform", "OSM_TYPE": "node", "OSM_ID": 3766625933 }, "geometry": { "type": "Point", "coordinates": [ -68.272230900000011, 12.1721201 ] } }
]
}
