{
"type": "FeatureCollection",
"crs": { "type": "name", "properties": { "name": "urn:ogc:def:crs:OGC:1.3:CRS84" } },
"features": [
{ "type": "Feature", "properties": { "NAME": null, "NAME_EN": null, "WATERWAY": "fuel", "OSM_TYPE": "node", "OSM_ID": 3857276487 }, "geometry": { "type": "Point", "coordinates": [ -68.2840851, 12.163598 ] } }
]
}
